pyHelfrag/__init__.py
pyHelfrag/_cooker.py
pyHelfrag/_registry.py
pyHelfrag/constants.py
pyHelfrag/modeode.py
pyHelfrag/pyHelfrag.py
pyHelfrag/rdaam.py
pyHelfrag/tThistory.py
pyHelfrag/utilities.py
pyHelfrag-0.2.dist-info/DESCRIPTION.rst
pyHelfrag-0.2.dist-info/METADATA
pyHelfrag-0.2.dist-info/RECORD
pyHelfrag-0.2.dist-info/WHEEL
pyHelfrag-0.2.dist-info/metadata.json
pyHelfrag-0.2.dist-info/top_level.txt
