Metadata-Version: 2.0
Name: pyHelfrag
Version: 0.2
Summary: Generate (U-Th)/He Apatite fragment ages
Home-page: UNKNOWN
Author: Romain Beucher
Author-email: romain.beucher@unimelb.edu.au
License: MIT
Keywords: apatite,diffusion,helfrag,U-Th/He
Platform: UNKNOWN
Classifier: License :: OSI Approved :: MIT License
Classifier: Programming Language :: Python :: 2
Classifier: Programming Language :: Python :: 2.6
Classifier: Programming Language :: Python :: 2.7
Requires-Dist: matplotlib
Requires-Dist: numpy
Requires-Dist: pandas
Requires-Dist: scipy
Requires-Dist: tqdm
